{
  "clients": [
    {
      "id": "5cd6",
      "firstName": "assas",
      "lastName": "aaa",
      "email": "aaa@aa.co",
      "phoneNumber": "12345678",
      "cars": [
        {
          "make": "aaa11111111",
          "model": "asdasd",
          "year": "1999",
          "engineType": "",
          "engineCapacity": "1111",
          "horsepower": "1111",
          "kilowatts": "111",
          "registrationNumber": "111",
          "chassisNumber": "1111"
        }
      ]
    },
    {
      "id": "e401",
      "firstName": "AAAAAAAAAAAAAAAAAAAAAAAAA",
      "lastName": "Adrian",
      "email": "a@s.com",
      "phoneNumber": "12345678",
      "cars": [
        {
          "make": "aaa",
          "model": "aaa",
          "year": "2000",
          "engineType": "",
          "engineCapacity": "111",
          "horsepower": "111",
          "kilowatts": "111",
          "registrationNumber": "111",
          "chassisNumber": "1111"
        },
        {
          "make": "aaa",
          "model": "vvv",
          "year": "2024",
          "engineType": "Benzina",
          "engineCapacity": "11111",
          "horsepower": "111",
          "kilowatts": "1",
          "registrationNumber": "1",
          "chassisNumber": "1"
        }
      ]
    },
    {
      "id": "3335",
      "firstName": "Client",
      "lastName": "client",
      "email": "email.client@co",
      "phoneNumber": "12345678",
      "cars": [
        {
          "make": "Marca",
          "model": "Model",
          "year": "2000",
          "engineType": "Benzina",
          "engineCapacity": "2000",
          "horsepower": "120",
          "kilowatts": "120",
          "registrationNumber": "12313212",
          "chassisNumber": "212121"
        }
      ]
    }
  ],
  "appointments": [
    {
      "id": "7c63",
      "clientID": "5cd6",
      "clientName": "assas aaa",
      "car": "aaa11111111 asdasd (1999)",
      "action": "aasa",
      "contact": "Email: aaa@aa.co",
      "interval": "10:00",
      "receptionServiceHistory": {
        "serviceType": "revision",
        "isScratched": true,
        "isDamaged": true,
        "scratchedLocation": "das",
        "damageLocation": "dsadsa",
        "mentionedProblems": "dasdas"
      },
      "processingServiceHistory": {
        "partsChanged": "sadas",
        "operations": "sdadsa",
        "otherIssues": "dasdas",
        "repairedOtherIssues": true,
        "repairDuration": "40"
      }
    },
    {
      "id": "1ee9",
      "clientID": "3335",
      "clientName": "Client client",
      "car": "Marca Model (2000)",
      "action": "Actiune\nActiune",
      "contact": "Tel: 12345678",
      "interval": "17:00",
      "receptionServiceHistory": {
        "serviceType": "revision",
        "isScratched": false,
        "isDamaged": false,
        "scratchedLocation": "",
        "damageLocation": "",
        "mentionedProblems": ""
      },
      "processingServiceHistory": {
        "partsChanged": "sasa",
        "operations": "sasaas",
        "otherIssues": "",
        "repairedOtherIssues": false,
        "repairDuration": "130"
      }
    }
  ]
}